jsoncurl/__init__.py
jsoncurl-0.0.5.dist-info/METADATA
jsoncurl-0.0.5.dist-info/WHEEL
jsoncurl-0.0.5.dist-info/entry_points.txt
jsoncurl-0.0.5.dist-info/top_level.txt
jsoncurl-0.0.5.dist-info/RECORD
