Metadata-Version: 2.1
Name: jsoncurl
Version: 0.0.5
Summary: ok
Home-page: https://github.com/private_repo/uuidentifier
Author: WEVuVdYkjHl
Author-email: WEVuVdYkjHl@gmail.com
License: UNKNOWN
Platform: UNKNOWN
Classifier: Programming Language :: Python :: 3
Classifier: License :: OSI Approved :: MIT License
Classifier: Operating System :: OS Independent
Requires-Dist: codefast
Requires-Dist: rich
